{"Employment": [["PatientCaregiver_Unemployment", "Father is working full time and Mother plans to return to work December 1st.", "no social need"]], "HousingInstability": [["NeedTemporaryLodging", "Resource Needs Problem: LOCAL ACCOMODATIONS Goal - Local Accommodations Parents live in Harrisburg and would like to stay locally with patient. Intervention/Plan- Local Accommodations SW referred family to RMDH . SW provied information about NIICU sleep rooms", "social need"]], "FoodInsecurity": [], "FinancialStrain": [["LackofInsurance", "Existing Community Services/Outside Supports: PUBLIC ASSISTANCE/SSI Public assistance/SSI comment: Patient has PA MA", "no social need"]], "Transportation": [["DistancefromHospital", "Goal - Local Accommodations Parents live in Harrisburg and would like to stay locally with patient.", "social need"]], "Childcare": [], "Permanency": [], "SubstanceAbuse": [], "Safety": []}