{"Employment": [], "HousingInstability": [], "FoodInsecurity": [], "FinancialStrain": [], "Transportation": [], "Childcare": [], "Permanency": [], "SubstanceAbuse": [], "Safety": [["HomeEnvironment_Other", "Additional Comments: At 1:11pm, SW again attempted to contact York County CYS caseworker Ashley Althoff (717-309-5324) but was unable to leave a voicemail due to mailbox being full. At 1:12pm, SW attempted to reach CYS Supervisor Jessica Jones (717-683-7521) but mailbox was full and SW was unable to leave a message. At 1:14pm, SW attempted to contact CYS Manager, Vicky Weaver (717-781-4189) but mailbox was full and SW was unable to leave a message. SW continues efforts to connect with York County CYS.", "social need"]]}