{"Employment": [], "Housing": [], "Food": [], "Financial": [["LackofInsurance", "Existing Community Services/Outside Supports: PUBLIC ASSISTANCE/SSI Public assistance/SSI comment: patient has PA MA", "no social need"]], "Transportation": [], "Childcare": [], "SubstanceAbuse": [["DrugUse", "Substance Abuse YES Substance Abuse comment: Patient exposed to  multiple substances in utero, CYS now has custody", "social need"], ["DrugUse", "Parent Stressors Mother's substance use, patient's premature birth and illness, CYS involvement", "social need"]], "Safety": [["HomeEnvironment_Other", "CPS Involvement YES CPS involvment comment: CYS has custody of Serenity for all medical decisions", "social need"], ["HomeEnvironment_Other", "Parent Stressors Mother's substance use, patient's premature birth and illness, CYS involvement", "social need"], ["HomeEnvironment_Other", "Patient living situation: CHILDREN IN THE HOME;PARENT(S) Parent Information: Joanna  Mongiello ( mother) lives in Chester County, PA.  Per CYS she must have supervised visits at the hosptial. She is able to recieve medical updates.   Victor Garza ( Patient's father ) lives in Chester County, PA . There are no restrictions in place for him", "social need"]], "Permanency": [["NonPermanentPlacement", "CPS Involvement YES CPS involvment comment: CYS has custody of Serenity for all medical decisions", "social need"], ["NonPermanentPlacement", "Substance Abuse YES Substance Abuse comment: Patient exposed to  multiple substances in utero, CYS now has custody", "social need"], ["NonPermanentPlacement", "Patient living situation: CHILDREN IN THE HOME;PARENT(S", "no social need"]]}