{"Employment": [["Mom not working at this time.", "social need"]], "Housing": [], "Food": [], "Financial": [["Patient screened today for concrete resource eligibility: Patient is eligible and Social Work provided the following resources:  Meal Vouchers: 4 in total. (2) Tuesday and (2) Wednesday. . Additional comments: SW approved four meal vouchers and two gift cards ($50) for gas.", "social need"]], "Transportation": [["Mom travel approx two hours aware to care for siblings and patient.", "social need"]], "Childcare": [], "SubstanceAbuse": [], "Safety": [], "Permanency": []}