{"Employment": [], "Housing": [], "Food": [], "Financial": [], "Transportation": [], "Childcare": [], "SubstanceAbuse": [], "Safety": [["Problem: RESOURCE NEEDS Goal: Patient/family/caregiver will have coordination between medical team and current CPS providers to support care needs Outcome: Ongoing Progress:  SW spoke with DHS Case worker who confirmed that patient was officially and fully committed to OPC today in front of a judge at court and everything has been sent to Harrisburg for ICPC process to initiate.", "social need"]], "Permanency": [["Progress:  SW spoke with DHS Case worker who confirmed that patient was officially and fully committed to OPC today in front of a judge at court and everything has been sent to Harrisburg for ICPC process to initiate.", "social need"]]}