{"Employment": [], "Housing": [], "Food": [], "Financial": [["Pt will be scheduled with outpatient follow-up appts post D/C and will need to be set up with Modivcare for these appts.", "no social need"], ["Covering SW confirmed that pt is eligible for Modivcare transportation with the following.", "no social need"]], "Transportation": [["Pt will be scheduled with outpatient follow-up appts post D/C and will need to be set up with Modivcare for these appts.", "social need"], ["Covering SW confirmed that pt is eligible for Modivcare transportation with the following.", "social need"]], "Childcare": [], "SubstanceAbuse": [], "Safety": [], "Permanency": []}