{"Employment": [], "Housing": [], "Food": [], "Financial": [], "Transportation": [], "Childcare": [], "SubstanceAbuse": [], "Safety": [], "Permanency": [["Progress: SW and Case management called Mrs. Melise-Grant with DCF in NJ to update her on pateint status and discuss the plan for placement to Phoenix Center for Rehabilitation and Pediatrics. Mrs. Melise -Grant confirmed the original plan was to try to discharge to Voorhees Pediactric Facility however they did not have a bed available and had not agreed to an admission following receipt of medical records. Case Mgmt will submit clinical information to Phoenix today for review.", "social need"]]}