{"Employment": [["PatientCaregiver_Unemployment", "Grandmom is doing well post-surgery and is returning back to work today. She was hoping to do some training but the educator comes in at 2pm and grandmom has to leave to get to work.", "no social need"]], "Housing": [], "Food": [], "Financial": [], "Transportation": [], "Childcare": [], "SubstanceAbuse": [], "Safety": [], "Permanency": [["PermanentPlacementPending", "SW informed grandmother that we are still pursuing transitional care but both she and mom should continue training until a bed becomes available.", "social need"]]}