{"Employment": [["PatientCaregiver_Unemployment", "Patient's mother is self employed and currenlty out on leave. Patient's father is a paralegal and is back to work.", "no social need"]], "Housing": [], "Food": [], "Financial": [["LackofInsurance", "Resource Needs Problem(s) INSURANCE Goal - Insurance Patient will have active insurance. Intervention/Plan - Insurance Parents are in the process of deciding which insurance to add patient too. SW has also made a referral FHCP to help assist parents with either medicaid primary or PH-95.", "social need"]], "Transportation": [["DistancefromHospital", "Parent Stressors Being far away from home and adjusting to patient's hospitalization", "social need"], ["DistancefromHospital", "Parents live about an hour away and plan to visit each day.", "social need"]], "Childcare": [], "SubstanceAbuse": [], "Safety": [["HomeEnvironment_Other", "Relationships/Behavior Problem(s) VISITATION CONCERNS Goal - Visitation concerns Visitation Intervention/Plan - Visitation concerns Patient's father must be escorted to and from the bedside by security. Please see visitor rescriction for more information.", "social need"]], "Permanency": [["NonPermanentPlacement", "Patient living situation: PARENT(S)", "no social need"]]}